MANIFEST.in
PYPI_DESCRIPTION.rst
README.rst
setup.cfg
setup.py
taminsdk/__init__.py
taminsdk/exceptions.py
taminsdk/session.py
taminsdk.egg-info/PKG-INFO
taminsdk.egg-info/SOURCES.txt
taminsdk.egg-info/dependency_links.txt
taminsdk.egg-info/requires.txt
taminsdk.egg-info/top_level.txt
taminsdk/resources/__init__.py
taminsdk/resources/prescription/__init__.py
taminsdk/resources/prescription/exceptions.py
taminsdk/resources/prescription/helpers.py
taminsdk/resources/prescription/prescriptions.py
taminsdk/resources/prescription/types.py
taminsdk/resources/service/__init__.py
taminsdk/resources/service/exceptions.py
taminsdk/resources/service/helpers.py
taminsdk/resources/service/services.py
taminsdk/resources/service/types.py