Metadata-Version: 2.1
Name: taminsdk
Version: 0.2.0
Summary: Unoffical Tamin SDK
Home-page: https://github.com/mazafard/tamin-sdk
Author: Mazafard
Author-email: mazafard@gmail.com
License: UNKNOWN
Platform: UNKNOWN
Classifier: Development Status :: 4 - Beta
Classifier: Topic :: Software Development
Classifier: License :: OSI Approved :: GNU Lesser General Public License v3 (LGPLv3)
Classifier: Operating System :: OS Independent
Classifier: Programming Language :: Python :: 2.7
Classifier: Programming Language :: Python :: 3
Classifier: Programming Language :: Python :: 3.6
Classifier: Programming Language :: Python :: Implementation :: CPython
